NaverSeries/BookInfo.py
NaverSeries/__init__.py
NaverSeries/search.py
Naver_Series-1.1.3b0.dist-info/METADATA
Naver_Series-1.1.3b0.dist-info/WHEEL
Naver_Series-1.1.3b0.dist-info/top_level.txt
Naver_Series-1.1.3b0.dist-info/RECORD
