Metadata-Version: 2.1
Name: Naver-Series
Version: 1.1.3.Beta
Summary: Naver Series module
Home-page: https://github.com/EGGnmad/NaverSeries
Author: EGGnmad
Author-email: viewnono1219@gmail.com
License: UNKNOWN
Keywords: Naver,Naver Series,Book
Platform: UNKNOWN
Requires-Dist: requests (==2.26.0)
Requires-Dist: beautifulsoup4 (==4.10.0)
